Metadata-Version: 2.4
Name: mcp-server-pliakh
Version: 0.1.0
Summary: MCP server package
Author-email: Your Name <your@email.com>
License: MIT
Requires-Python: >=3.7
